{
  "interval": 60000,
  "priceAggregator": "median",
  "defaultSource": [
    "ftx"
  ],
  "sourceTimeout": 50000,
  "maxPriceDeviationPercent": 25,
  "evmChainId": 1,
  "tokens": {
    "YFI": {},
    "XRP": {},
    "AUDIO": {},
    "TRX": {},
    "STEP": {},
    "SRM": {},
    "SHIB": {},
    "SAND": {},
    "REN": {},
    "RAY": {},
    "PAXG": {},
    "BNT": {},
    "OMG": {},
    "OKB": {},
    "UNI": {},
    "MATIC": {},
    "DOGE": {},
    "LINK": {},
    "ENJ": {},
    "FTT": {},
    "BAND": {},
    "HT": {},
    "BAT": {},
    "SOL": {},
    "AAVE": {},
    "ZRX": {},
    "AKRO": {},
    "CEL": {},
    "ETH": {},
    "CHZ": {},
    "BCH": {},
    "AXS": {},
    "BNB": {},
    "BTC": {},
    "LRC": {},
    "COMP": {},
    "LTC": {},
    "MKR": {},
    "SNX": {},
    "REEF": {},
    "YFII": {},
    "STORJ": {},
    "SUSHI": {},
    "CRV": {},
    "SUN": {},
    "DAI": {},
    "BADGER": {},
    "GRT": {},
    "WBTC": {},
    "1INCH": {},
    "DODO": {},
    "OXY": {},
    "CHR": {},
    "RUNE": {},
    "SLP": {},
    "C98": {},
    "MAPS": {},
    "FIDA": {},
    "EXCHBEAR": {},
    "BEAR": {},
    "ETHBULL": {},
    "BVOL": {},
    "LINA": {},
    "ALTBEAR": {},
    "BNBBEAR": {},
    "XRPBULL": {},
    "GT": {},
    "EXCHBULL": {},
    "BNBBULL": {},
    "FRONT": {},
    "ASD": {},
    "XRPBEAR": {},
    "ALTBULL": {},
    "EOSBEAR": {},
    "HGET": {},
    "BULL": {},
    "CRO": {},
    "FTM": {},
    "LTCBEAR": {},
    "IBVOL": {},
    "LTCBULL": {},
    "PROM": {},
    "BAL": {},
    "RAMP": {},
    "SXP": {},
    "ORBS": {},
    "JST": {},
    "ALCX": {},
    "WAVES": {},
    "MTL": {},
    "TOMO": {},
    "DENT": {},
    "EUR": {},
    "WRX": {},
    "STMX": {},
    "KNC": {},
    "GBP": {},
    "RSR": {},
    "HNT": {},
    "ALPHA": {},
    "SKL": {},
    "PERP": {},
    "PUNDIX": {},
    "USDT": {},
    "LEO": {},
    "AMPL": {},
    "XAUT": {},
    "MOB": {},
    "AMC": {},
    "MATH": {},
    "AAPL": {},
    "ABNB": {},
    "ACB": {},
    "ADABEAR": {},
    "ADABULL": {},
    "AMD": {},
    "AMZN": {},
    "ARKK": {},
    "BABA": {},
    "BB": {},
    "BILI": {},
    "BITW": {},
    "BNTX": {},
    "BRZ": {},
    "BYND": {},
    "CGC": {},
    "COIN": {},
    "CRON": {},
    "DOGEBULL": {},
    "FB": {},
    "GDXJ": {},
    "GLD": {},
    "GLXY": {},
    "GME": {},
    "GOOGL": {},
    "HXRO": {},
    "MRNA": {},
    "NFLX": {},
    "NIO": {},
    "NOK": {},
    "NVDA": {},
    "PENN": {},
    "PFE": {},
    "PYPL": {},
    "ROOK": {},
    "SLV": {},
    "SPY": {},
    "SQ": {},
    "TRYB": {},
    "TSLA": {},
    "TSM": {},
    "TWTR": {},
    "UBER": {},
    "USO": {},
    "ZM": {},
    "CLV": {},
    "CQT": {},
    "CREAM": {},
    "MTA": {},
    "GDX": {},
    "TLRY": {},
    "DKNG": {},
    "BAO": {},
    "CONV": {},
    "CUSDT": {},
    "DMG": {},
    "KIN": {},
    "UBXT": {},
    "BCHBEAR": {},
    "BCHBULL": {},
    "BSVBEAR": {},
    "BSVBULL": {},
    "LINKBEAR": {},
    "LINKBULL": {},
    "TRXBEAR": {},
    "TRXBULL": {},
    "XLMBEAR": {},
    "XLMBULL": {}
  }
}
