{
  "interval": 60000,
  "priceAggregator": "median",
  "defaultSource": [
    "huobipro"
  ],
  "sourceTimeout": 50000,
  "maxPriceDeviationPercent": 25,
  "evmChainId": 1,
  "tokens": {
    "ZEN": {},
    "YFI": {},
    "XRP": {},
    "USDC": {},
    "TRX": {},
    "THETA": {},
    "ETC": {},
    "SHIB": {},
    "SAND": {},
    "REN": {},
    "CVC": {},
    "BNT": {},
    "OMG": {},
    "UNI": {},
    "UMA": {},
    "FIL": {},
    "MATIC": {},
    "DOCK": {},
    "DOGE": {},
    "LINK": {},
    "ENJ": {},
    "FTT": {},
    "ZIL": {},
    "BTT": {},
    "PAX": {},
    "EOS": {},
    "BAND": {},
    "ZEC": {},
    "HT": {},
    "BAT": {},
    "SOL": {},
    "AAVE": {},
    "ZRX": {},
    "AKRO": {},
    "XLM": {},
    "MANA": {},
    "VET": {},
    "QTUM": {},
    "ETH": {},
    "CHZ": {},
    "DOT": {},
    "SOC": {},
    "BCH": {},
    "AXS": {},
    "NEO": {},
    "ADA": {},
    "BTC": {},
    "BSV": {},
    "KSM": {},
    "LRC": {},
    "COMP": {},
    "LTC": {},
    "MKR": {},
    "SNX": {},
    "REEF": {},
    "DASH": {},
    "XMR": {},
    "IOTA": {},
    "GXC": {},
    "ONT": {},
    "BTM": {},
    "IOST": {},
    "XEM": {},
    "AE": {},
    "ALGO": {},
    "ICX": {},
    "CTXC": {},
    "ELF": {},
    "LAMB": {},
    "LOOM": {},
    "WTC": {},
    "YFII": {},
    "STORJ": {},
    "SUSHI": {},
    "PEARL": {},
    "CRV": {},
    "XRT": {},
    "CVP": {},
    "VALUE": {},
    "SUN": {},
    "DAI": {},
    "GOF": {},
    "PHA": {},
    "SWRV": {},
    "BLZ": {},
    "RING": {},
    "SC": {},
    "AVAX": {},
    "AR": {},
    "CRU": {},
    "NEAR": {},
    "NSURE": {},
    "API3": {},
    "NU": {},
    "BADGER": {},
    "GRT": {},
    "OXT": {},
    "WBTC": {},
    "1INCH": {},
    "AUCTION": {},
    "YAM": {},
    "INJ": {},
    "MASK": {},
    "MIR": {},
    "POND": {},
    "FLOW": {},
    "MDX": {},
    "NKN": {},
    "XCH": {},
    "APN": {},
    "FORTH": {},
    "LAT": {},
    "CSPR": {},
    "ICP": {},
    "CHR": {},
    "O3": {},
    "NFT": {},
    "MLN": {},
    "CTSI": {},
    "RLC": {},
    "ATOM": {},
    "STAKE": {},
    "KAVA": {},
    "RVN": {},
    "LINA": {},
    "CKB": {},
    "GT": {},
    "STPT": {},
    "FRONT": {},
    "CRO": {},
    "WOO": {},
    "XTZ": {},
    "ONE": {},
    "FIS": {},
    "ANKR": {},
    "HBAR": {},
    "NEXO": {},
    "BIX": {},
    "FSN": {},
    "FOR": {},
    "IRIS": {},
    "NEST": {},
    "BAL": {},
    "TRB": {},
    "WNXM": {},
    "ANT": {},
    "LHB": {},
    "FILDA": {},
    "MXC": {},
    "GNX": {},
    "JST": {},
    "XEC": {},
    "NULS": {},
    "WAVES": {},
    "NANO": {},
    "HC": {},
    "ARPA": {},
    "IOTX": {},
    "OGN": {},
    "BTS": {},
    "HIVE": {},
    "KNC": {},
    "DCR": {},
    "LUNA": {},
    "RSR": {},
    "NBS": {},
    "UTK": {},
    "SKL": {},
    "FIRO": {},
    "POLS": {},
    "RNDR": {},
    "INSUR": {},
    "SNT": {},
    "WAXP": {},
    "VSYS": {},
    "KAN": {},
    "BHD": {},
    "ELA": {},
    "SKM": {},
    "STEEM": {},
    "WICC": {},
    "BAGS": {},
    "ZKS": {},
    "CAN": {},
    "SMT": {},
    "OGO": {},
    "ATP": {},
    "PAI": {},
    "GLM": {},
    "EKT": {},
    "HPT": {},
    "ACT": {},
    "NAS": {},
    "NODE": {},
    "CMT": {},
    "MX": {},
    "RUFF": {},
    "NEW": {},
    "PVT": {},
    "HBC": {},
    "MDS": {},
    "OCN": {},
    "WXT": {},
    "DTA": {},
    "ITC": {},
    "CNNS": {},
    "TOP": {},
    "TT": {},
    "LOL": {},
    "VIDY": {},
    "CRE": {},
    "EGT": {},
    "MTA": {},
    "SEELE": {},
    "AST": {},
    "ABT": {},
    "YEE": {},
    "DF": {},
    "SWFTC": {},
    "MASS": {},
    "BETH": {},
    "KCASH": {},
    "DHT": {}
  }
}
